[
{"6PY8": {"Ig domain" : 1, "igs": [
{"6PY8_C": {
"6PY8_C,0_30:339:2329": {
"refpdbname":"RBPJ_6py8C_human_Unk-n1", "score":0.872, "seqid":1, "nresAlign":109, "data": [{"6PY8_C_31_D": "A1545"},
{"6PY8_C_32_Q": "A1546"},
{"6PY8_C_33_T": "A1547"},
{"6PY8_C_34_V": "A1548"},
{"6PY8_C_35_L": "A1549"},
{"6PY8_C_36_I": "A1550"},
{"6PY8_C_37_L": "A1551"},
{"6PY8_C_38_H": "A1552"},
{"6PY8_C_39_A": "A1553"},
{"6PY8_C_40_K": "A'1848"},
{"6PY8_C_41_V": "A'1849"},
{"6PY8_C_42_A": "A'1850"},
{"6PY8_C_43_Q": "A'1851"},
{"6PY8_C_44_K": "A'1852"},
{"6PY8_C_45_S": "A'1853_loop"},
{"6PY8_C_46_Y": "A'1854_loop"},
{"6PY8_C_47_G": "A'1855_loop"},
{"6PY8_C_48_N": "A'1856_loop"},
{"6PY8_C_49_E": "A'1857_loop"},
{"6PY8_C_50_K": "A'1858_loop"},
{"6PY8_C_51_R": "B2541_loop"},
{"6PY8_C_52_F": "B2542_loop"},
{"6PY8_C_53_F": "B2543_loop"},
{"6PY8_C_54_C": "B2544_loop"},
{"6PY8_C_55_P": "B2545_loop"},
{"6PY8_C_56_P": "B2546"},
{"6PY8_C_57_P": "B2547"},
{"6PY8_C_58_C": "B2548"},
{"6PY8_C_59_V": "B2549"},
{"6PY8_C_60_Y": "B2550"},
{"6PY8_C_61_L": "B2551"},
{"6PY8_C_62_M": "B2552"},
{"6PY8_C_63_G": "B2553"},
{"6PY8_C_64_S": "B2554_loop"},
{"6PY8_C_65_G": "B2555_loop"},
{"6PY8_C_66_W": "B2556_loop"},
{"6PY8_C_67_K": "B2557_loop"},
{"6PY8_C_68_K": "B2558_loop"},
{"6PY8_C_69_K": "B2559_loop"},
{"6PY8_C_70_K": "B2560_loop"},
{"6PY8_C_71_E": "B2561_loop"},
{"6PY8_C_72_Q": "B2562_loop"},
{"6PY8_C_73_M": "B2563_loop"},
{"6PY8_C_74_E": "C3535_loop"},
{"6PY8_C_75_R": "C3536_loop"},
{"6PY8_C_76_D": "C3537_loop"},
{"6PY8_C_77_G": "C3538_loop"},
{"6PY8_C_78_C": "C3539_loop"},
{"6PY8_C_79_S": "C3540_loop"},
{"6PY8_C_80_E": "C3541_loop"},
{"6PY8_C_81_Q": "C3542_loop"},
{"6PY8_C_82_E": "C3543_loop"},
{"6PY8_C_83_S": "C3544_loop"},
{"6PY8_C_84_Q": "C3545"},
{"6PY8_C_85_P": "C3546"},
{"6PY8_C_86_C": "C3547"},
{"6PY8_C_87_A": "C3548"},
{"6PY8_C_88_F": "C3549"},
{"6PY8_C_89_I": "C3550"},
{"6PY8_C_90_G": "C3551"},
{"6PY8_C_91_I": "C3552"},
{"6PY8_C_92_G": "C3553_loop"},
{"6PY8_C_93_N": "C3554_loop"},
{"6PY8_C_94_S": "C3555_loop"},
{"6PY8_C_95_D": "C'4546_loop"},
{"6PY8_C_96_Q": "C'4547_loop"},
{"6PY8_C_97_E": "C'4548_loop"},
{"6PY8_C_98_M": "C'4549"},
{"6PY8_C_99_Q": "C'4550"},
{"6PY8_C_100_Q": "C'4551"},
{"6PY8_C_101_L": "C'4552"},
{"6PY8_C_102_N": "C'4553_loop"},
{"6PY8_C_103_L": "C'4554_loop"},
{"6PY8_C_104_E": "C'4555_loop"},
{"6PY8_C_105_G": "E7544_loop"},
{"6PY8_C_106_K": "E7545_loop"},
{"6PY8_C_107_N": "E7546"},
{"6PY8_C_108_Y": "E7547"},
{"6PY8_C_109_C": "E7548"},
{"6PY8_C_110_T": "E7549"},
{"6PY8_C_111_A": "E7550"},
{"6PY8_C_112_K": "E7551"},
{"6PY8_C_113_T": "E7552_loop"},
{"6PY8_C_114_L": "E7553_loop"},
{"6PY8_C_115_Y": "E7554_loop"},
{"6PY8_C_116_I": "E7555_loop"},
{"6PY8_C_117_S": "E7556_loop"},
{"6PY8_C_118_D": "F8539_loop"},
{"6PY8_C_119_S": "F8540_loop"},
{"6PY8_C_120_D": "F8541_loop"},
{"6PY8_C_121_K": "F8542_loop"},
{"6PY8_C_122_R": "F8543_loop"},
{"6PY8_C_123_K": "F8544"},
{"6PY8_C_124_H": "F8545"},
{"6PY8_C_125_F": "F8546"},
{"6PY8_C_126_M": "F8547"},
{"6PY8_C_127_L": "F8548"},
{"6PY8_C_128_S": "F8549"},
{"6PY8_C_129_V": "F8550"},
{"6PY8_C_130_K": "F8551"},
{"6PY8_C_131_M": "F8552"},
{"6PY8_C_132_F": "F8553"},
{"6PY8_C_133_Y": "F8554"},
{"6PY8_C_134_G": "F8555"},
{"6PY8_C_135_N": "F8556_loop"},
{"6PY8_C_136_S": "G9544"},
{"6PY8_C_137_D": "G9545"},
{"6PY8_C_138_D": "G9546"},
{"6PY8_C_139_I": "G9547"},
{"6PY8_C_140_G": "G9548"},
{"6PY8_C_141_V": "G9549"},
{"6PY8_C_142_F": "G9550"},
{"6PY8_C_143_L": "G9551"},
{"6PY8_C_144_S": "G9552"},
{"6PY8_C_145_K": "G9553"},
{"6PY8_C_146_R": "G9554"},
{"6PY8_C_147_I": "G9555"},
{"6PY8_C_148_K": "G9556"},
{"6PY8_C_149_V": "G9557"},
{"6PY8_C_150_I": "G9558"},
{"6PY8_C_151_S": "G9559"},
],
},
"6PY8_C,0_30:439:3116": {
"refpdbname":"RBPJ_6py8C_human_Unk-n2", "score":1, "seqid":1, "nresAlign":126, "data": [{"6PY8_C_341_P": "A1545"},
{"6PY8_C_342_V": "A1546"},
{"6PY8_C_343_V": "A1547"},
{"6PY8_C_344_E": "A1548"},
{"6PY8_C_345_S": "A1549"},
{"6PY8_C_346_L": "A1550"},
{"6PY8_C_347_Q": "A1551"},
{"6PY8_C_348_L": "A1552"},
{"6PY8_C_349_N": "A1553"},
{"6PY8_C_350_G": "A1554"},
{"6PY8_C_351_G": "A1555"},
{"6PY8_C_352_G": "A1556_loop"},
{"6PY8_C_353_D": "B2544_loop"},
{"6PY8_C_354_V": "B2545"},
{"6PY8_C_355_A": "B2546"},
{"6PY8_C_356_M": "B2547"},
{"6PY8_C_357_L": "B2548"},
{"6PY8_C_358_E": "B2549"},
{"6PY8_C_359_L": "B2550"},
{"6PY8_C_360_T": "B2551"},
{"6PY8_C_361_G": "B2552"},
{"6PY8_C_362_Q": "B2553"},
{"6PY8_C_363_N": "B2554"},
{"6PY8_C_364_F": "B2555_loop"},
{"6PY8_C_365_T": "B2556_loop"},
{"6PY8_C_366_P": "C3544_loop"},
{"6PY8_C_367_N": "C3545"},
{"6PY8_C_368_L": "C3546"},
{"6PY8_C_369_R": "C3547"},
{"6PY8_C_370_V": "C3548"},
{"6PY8_C_371_W": "C3549"},
{"6PY8_C_372_F": "C3550"},
{"6PY8_C_373_G": "C3551"},
{"6PY8_C_374_D": "C3552_loop"},
{"6PY8_C_375_V": "C3553_loop"},
{"6PY8_C_376_E": "D6547_loop"},
{"6PY8_C_377_A": "D6548_loop"},
{"6PY8_C_378_E": "D6549"},
{"6PY8_C_379_T": "D6550"},
{"6PY8_C_380_M": "D6551"},
{"6PY8_C_381_Y": "D6552"},
{"6PY8_C_382_R": "D6553"},
{"6PY8_C_383_C": "D6554"},
{"6PY8_C_384_G": "E7545"},
{"6PY8_C_385_E": "E7546"},
{"6PY8_C_386_S": "E7547"},
{"6PY8_C_387_M": "E7548"},
{"6PY8_C_388_L": "E7549"},
{"6PY8_C_389_C": "E7550"},
{"6PY8_C_390_V": "E7551"},
{"6PY8_C_391_V": "E7552"},
{"6PY8_C_392_P": "E7553_loop"},
{"6PY8_C_393_D": "E7554_loop"},
{"6PY8_C_394_I": "E7555_loop"},
{"6PY8_C_395_S": "E7556_loop"},
{"6PY8_C_396_A": "E7557_loop"},
{"6PY8_C_397_F": "E7558_loop"},
{"6PY8_C_398_R": "E7559_loop"},
{"6PY8_C_399_E": "F8537_loop"},
{"6PY8_C_400_G": "F8538_loop"},
{"6PY8_C_401_W": "F8539_loop"},
{"6PY8_C_402_R": "F8540_loop"},
{"6PY8_C_403_W": "F8541_loop"},
{"6PY8_C_404_V": "F8542_loop"},
{"6PY8_C_405_R": "F8543"},
{"6PY8_C_406_Q": "F8544"},
{"6PY8_C_407_P": "F8545"},
{"6PY8_C_408_V": "F8546"},
{"6PY8_C_409_Q": "F8547"},
{"6PY8_C_410_V": "F8548"},
{"6PY8_C_411_P": "F8549"},
{"6PY8_C_412_V": "F8550"},
{"6PY8_C_413_T": "F8551"},
{"6PY8_C_414_L": "F8552"},
{"6PY8_C_415_V": "F8553"},
{"6PY8_C_416_R": "F8554"},
{"6PY8_C_417_N": "F8555"},
{"6PY8_C_418_D": "F8556_loop"},
{"6PY8_C_419_G": "G9545"},
{"6PY8_C_420_I": "G9546"},
{"6PY8_C_421_I": "G9547"},
{"6PY8_C_422_Y": "G9548"},
{"6PY8_C_423_S": "G9549"},
{"6PY8_C_424_T": "G9550"},
{"6PY8_C_425_S": "G9551"},
{"6PY8_C_426_L": "G9552"},
{"6PY8_C_427_T": "G9553"},
{"6PY8_C_428_F": "G9554"},
{"6PY8_C_429_T": "G9555"},
{"6PY8_C_430_Y": "G9556"},
{"6PY8_C_431_T": "G9557"},
{"6PY8_C_432_P": "G9558"},
{"6PY8_C_433_E": "G9559"},
],
},
}},
{"6PY8_E": {
"6PY8_E,0_30:339:2320": {
"refpdbname":"RBPJ_6py8C_human_Unk-n1", "score":0.845363, "seqid":1, "nresAlign":108, "data": [{"6PY8_E_31_D": "A1545"},
{"6PY8_E_32_Q": "A1546"},
{"6PY8_E_33_T": "A1547"},
{"6PY8_E_34_V": "A1548"},
{"6PY8_E_35_L": "A1549"},
{"6PY8_E_36_I": "A1550"},
{"6PY8_E_37_L": "A1551"},
{"6PY8_E_38_H": "A1552"},
{"6PY8_E_39_A": "A1553"},
{"6PY8_E_40_K": "A'1848"},
{"6PY8_E_41_V": "A'1849"},
{"6PY8_E_42_A": "A'1850"},
{"6PY8_E_43_Q": "A'1851"},
{"6PY8_E_44_K": "A'1852"},
{"6PY8_E_45_S": "A'1853_loop"},
{"6PY8_E_46_Y": "A'1854_loop"},
{"6PY8_E_47_G": "A'1855_loop"},
{"6PY8_E_48_N": "A'1856_loop"},
{"6PY8_E_49_E": "A'1857_loop"},
{"6PY8_E_50_K": "A'1858_loop"},
{"6PY8_E_51_R": "B2541_loop"},
{"6PY8_E_52_F": "B2542_loop"},
{"6PY8_E_53_F": "B2543_loop"},
{"6PY8_E_54_C": "B2544_loop"},
{"6PY8_E_55_P": "B2545_loop"},
{"6PY8_E_56_P": "B2546"},
{"6PY8_E_57_P": "B2547"},
{"6PY8_E_58_C": "B2548"},
{"6PY8_E_59_V": "B2549"},
{"6PY8_E_60_Y": "B2550"},
{"6PY8_E_61_L": "B2551"},
{"6PY8_E_62_M": "B2552"},
{"6PY8_E_63_G": "B2553"},
{"6PY8_E_64_S": "B2554_loop"},
{"6PY8_E_65_G": "B2555_loop"},
{"6PY8_E_66_W": "B2556_loop"},
{"6PY8_E_67_K": "B2557_loop"},
{"6PY8_E_68_K": "B2558_loop"},
{"6PY8_E_69_K": "B2559_loop"},
{"6PY8_E_70_K": "B2560_loop"},
{"6PY8_E_71_E": "B2561_loop"},
{"6PY8_E_72_Q": "B2562_loop"},
{"6PY8_E_73_M": "B2563_loop"},
{"6PY8_E_74_E": "C3535_loop"},
{"6PY8_E_75_R": "C3536_loop"},
{"6PY8_E_76_D": "C3537_loop"},
{"6PY8_E_77_G": "C3538_loop"},
{"6PY8_E_78_C": "C3539_loop"},
{"6PY8_E_79_S": "C3540_loop"},
{"6PY8_E_80_E": "C3541_loop"},
{"6PY8_E_81_Q": "C3542_loop"},
{"6PY8_E_82_E": "C3543_loop"},
{"6PY8_E_83_S": "C3544_loop"},
{"6PY8_E_84_Q": "C3545"},
{"6PY8_E_85_P": "C3546"},
{"6PY8_E_86_C": "C3547"},
{"6PY8_E_87_A": "C3548"},
{"6PY8_E_88_F": "C3549"},
{"6PY8_E_89_I": "C3550"},
{"6PY8_E_90_G": "C3551"},
{"6PY8_E_91_I": "C3552"},
{"6PY8_E_92_G": "C3553_loop"},
{"6PY8_E_93_N": "C3554_loop"},
{"6PY8_E_94_S": "C3555_loop"},
{"6PY8_E_95_D": "C'4546_loop"},
{"6PY8_E_96_Q": "C'4547_loop"},
{"6PY8_E_97_E": "C'4548_loop"},
{"6PY8_E_98_M": "C'4549"},
{"6PY8_E_99_Q": "C'4550"},
{"6PY8_E_100_Q": "C'4551"},
{"6PY8_E_101_L": "C'4552"},
{"6PY8_E_102_N": "C'4553"},
{"6PY8_E_103_L": "C'4554_loop"},
{"6PY8_E_104_E": "C'4555_loop"},
{"6PY8_E_105_G": "E7544_loop"},
{"6PY8_E_106_K": "E7545_loop"},
{"6PY8_E_107_N": "E7546"},
{"6PY8_E_108_Y": "E7547"},
{"6PY8_E_109_C": "E7548"},
{"6PY8_E_110_T": "E7549"},
{"6PY8_E_111_A": "E7550"},
{"6PY8_E_112_K": "E7551"},
{"6PY8_E_113_T": "E7552_loop"},
{"6PY8_E_114_L": "E7553_loop"},
{"6PY8_E_115_Y": "E7554_loop"},
{"6PY8_E_116_I": "E7555_loop"},
{"6PY8_E_117_S": "E7556_loop"},
{"6PY8_E_118_D": "F8539_loop"},
{"6PY8_E_119_S": "F8540_loop"},
{"6PY8_E_120_D": "F8541_loop"},
{"6PY8_E_121_K": "F8542_loop"},
{"6PY8_E_122_R": "F8543_loop"},
{"6PY8_E_123_K": "F8544"},
{"6PY8_E_124_H": "F8545"},
{"6PY8_E_125_F": "F8546"},
{"6PY8_E_126_M": "F8547"},
{"6PY8_E_127_L": "F8548"},
{"6PY8_E_128_S": "F8549"},
{"6PY8_E_129_V": "F8550"},
{"6PY8_E_130_K": "F8551"},
{"6PY8_E_131_M": "F8552"},
{"6PY8_E_132_F": "F8553"},
{"6PY8_E_133_Y": "F8554"},
{"6PY8_E_134_G": "F8555"},
{"6PY8_E_135_N": "F8556_loop"},
{"6PY8_E_136_S": "G9544"},
{"6PY8_E_137_D": "G9545"},
{"6PY8_E_138_D": "G9546"},
{"6PY8_E_139_I": "G9547"},
{"6PY8_E_140_G": "G9548"},
{"6PY8_E_141_V": "G9549"},
{"6PY8_E_142_F": "G9550"},
{"6PY8_E_143_L": "G9551"},
{"6PY8_E_144_S": "G9552"},
{"6PY8_E_145_K": "G9553"},
{"6PY8_E_146_R": "G9554"},
{"6PY8_E_147_I": "G9555"},
{"6PY8_E_148_K": "G9556"},
{"6PY8_E_149_V": "G9557"},
{"6PY8_E_150_I": "G9558"},
{"6PY8_E_151_S": "G9559"},
],
},
"6PY8_E,0_30:441:3119": {
"refpdbname":"RBPJ_6py8C_human_Unk-n2", "score":0.961457, "seqid":0.968254, "nresAlign":126, "data": [{"6PY8_E_341_P": "A1545"},
{"6PY8_E_342_V": "A1546"},
{"6PY8_E_343_V": "A1547"},
{"6PY8_E_344_E": "A1548"},
{"6PY8_E_345_S": "A1549"},
{"6PY8_E_346_L": "A1550"},
{"6PY8_E_347_Q": "A1551"},
{"6PY8_E_348_L": "A1552"},
{"6PY8_E_349_N": "A1553"},
{"6PY8_E_350_G": "A1554"},
{"6PY8_E_351_G": "A1555"},
{"6PY8_E_352_G": "A1556_loop"},
{"6PY8_E_353_D": "B2544_loop"},
{"6PY8_E_354_V": "B2545"},
{"6PY8_E_355_A": "B2546"},
{"6PY8_E_356_M": "B2547"},
{"6PY8_E_357_L": "B2548"},
{"6PY8_E_358_E": "B2549"},
{"6PY8_E_359_L": "B2550"},
{"6PY8_E_360_T": "B2551"},
{"6PY8_E_361_G": "B2552"},
{"6PY8_E_362_Q": "B2553"},
{"6PY8_E_363_N": "B2554"},
{"6PY8_E_364_F": "B2555_loop"},
{"6PY8_E_365_T": "B2556_loop"},
{"6PY8_E_366_P": "C3544_loop"},
{"6PY8_E_367_N": "C3545"},
{"6PY8_E_368_L": "C3546"},
{"6PY8_E_369_R": "C3547"},
{"6PY8_E_370_V": "C3548"},
{"6PY8_E_371_W": "C3549"},
{"6PY8_E_372_F": "C3550"},
{"6PY8_E_373_G": "C3551"},
{"6PY8_E_374_D": "C3552_loop"},
{"6PY8_E_375_V": "C3553_loop"},
{"6PY8_E_376_E": "D6547_loop"},
{"6PY8_E_377_A": "D6548_loop"},
{"6PY8_E_378_E": "D6549"},
{"6PY8_E_379_T": "D6550"},
{"6PY8_E_380_M": "D6551"},
{"6PY8_E_381_Y": "D6552"},
{"6PY8_E_382_R": "D6553"},
{"6PY8_E_383_C": "D6554"},
{"6PY8_E_384_G": "D6555_loop"},
{"6PY8_E_385_E": "E7546"},
{"6PY8_E_386_S": "E7547"},
{"6PY8_E_387_M": "E7548"},
{"6PY8_E_388_L": "E7549"},
{"6PY8_E_389_C": "E7550"},
{"6PY8_E_390_V": "E7551"},
{"6PY8_E_391_V": "E7552"},
{"6PY8_E_392_P": "E7553_loop"},
{"6PY8_E_393_D": "E7554_loop"},
{"6PY8_E_394_I": "E7555_loop"},
{"6PY8_E_395_S": "E7556_loop"},
{"6PY8_E_396_A": "E7557_loop"},
{"6PY8_E_397_F": "E7558_loop"},
{"6PY8_E_398_R": "E7559_loop"},
{"6PY8_E_399_E": "F8537_loop"},
{"6PY8_E_400_G": "F8538_loop"},
{"6PY8_E_401_W": "F8539_loop"},
{"6PY8_E_402_R": "F8540_loop"},
{"6PY8_E_403_W": "F8541_loop"},
{"6PY8_E_404_V": "F8542_loop"},
{"6PY8_E_405_R": "F8543"},
{"6PY8_E_406_Q": "F8544"},
{"6PY8_E_407_P": "F8545"},
{"6PY8_E_408_V": "F8546"},
{"6PY8_E_409_Q": "F8547"},
{"6PY8_E_410_V": "F8548"},
{"6PY8_E_411_P": "F8549"},
{"6PY8_E_412_V": "F8550"},
{"6PY8_E_413_T": "F8551"},
{"6PY8_E_414_L": "F8552"},
{"6PY8_E_415_V": "F8553"},
{"6PY8_E_416_R": "F8554"},
{"6PY8_E_417_N": "F8555"},
{"6PY8_E_418_D": "F8556_loop"},
{"6PY8_E_419_G": "G9545"},
{"6PY8_E_420_I": "G9546"},
{"6PY8_E_421_I": "G9547"},
{"6PY8_E_422_Y": "G9548"},
{"6PY8_E_423_S": "G9549"},
{"6PY8_E_424_T": "G9550"},
{"6PY8_E_425_S": "G9551"},
{"6PY8_E_426_L": "G9552"},
{"6PY8_E_427_T": "G9553"},
{"6PY8_E_428_F": "G9554"},
{"6PY8_E_429_T": "G9555"},
{"6PY8_E_430_Y": "G9556"},
{"6PY8_E_431_T": "G9557"},
{"6PY8_E_432_P": "G9558"},
{"6PY8_E_433_E": "G9559"},
],
},
}},
]}},


]
