[
{"Q7Z7D3": {"Ig domain" : 1, "igs": [
{"Q7Z7D3_A": {
"Q7Z7D3_A,0_35:269:993": {
"refpdbname":"VTCN1_Q7Z7D3_human_C1-n2", "score":0.567259, "seqid":0.095745, "nresAlign":94, "data": [{"Q7Z7D3_A_37_I": "A1545"},
{"Q7Z7D3_A_38_T": "A1546"},
{"Q7Z7D3_A_39_V": "A1547"},
{"Q7Z7D3_A_40_T": "A1548"},
{"Q7Z7D3_A_41_T": "A1549"},
{"Q7Z7D3_A_42_V": "A1550"},
{"Q7Z7D3_A_43_A": "A1551"},
{"Q7Z7D3_A_44_S": "A1552"},
{"Q7Z7D3_A_45_A": "A1553"},
{"Q7Z7D3_A_46_G": "A1554"},
{"Q7Z7D3_A_47_N": "A1555"},
{"Q7Z7D3_A_48_I": "A1556_loop"},
{"Q7Z7D3_A_49_G": "A1557_loop"},
{"Q7Z7D3_A_50_E": "B2545_loop"},
{"Q7Z7D3_A_51_D": "B2546_loop"},
{"Q7Z7D3_A_52_G": "B2547"},
{"Q7Z7D3_A_53_I": "B2548"},
{"Q7Z7D3_A_54_L": "B2549"},
{"Q7Z7D3_A_55_S": "B2550"},
{"Q7Z7D3_A_56_C": "B2551"},
{"Q7Z7D3_A_57_T": "B2552"},
{"Q7Z7D3_A_58_F": "B2553"},
{"Q7Z7D3_A_59_E": "B2554"},
{"Q7Z7D3_A_60_P": "B2555"},
{"Q7Z7D3_A_61_D": "B2556"},
{"Q7Z7D3_A_62_I": "B2557_loop"},
{"Q7Z7D3_A_63_K": "B2558_loop"},
{"Q7Z7D3_A_64_L": "B2559_loop"},
{"Q7Z7D3_A_65_S": "C3544_loop"},
{"Q7Z7D3_A_66_D": "C3545_loop"},
{"Q7Z7D3_A_67_I": "C3546_loop"},
{"Q7Z7D3_A_68_V": "C3547"},
{"Q7Z7D3_A_69_I": "C3548"},
{"Q7Z7D3_A_70_Q": "C3549"},
{"Q7Z7D3_A_71_W": "C3550"},
{"Q7Z7D3_A_72_L": "C3551"},
{"Q7Z7D3_A_73_K": "C3552"},
{"Q7Z7D3_A_74_E": "C3553"},
{"Q7Z7D3_A_75_G": "C3554_loop"},
{"Q7Z7D3_A_76_V": "C3555_loop"},
{"Q7Z7D3_A_77_L": "C'4547_loop"},
{"Q7Z7D3_A_78_G": "C'4548"},
{"Q7Z7D3_A_79_L": "C'4549"},
{"Q7Z7D3_A_80_V": "C'4550"},
{"Q7Z7D3_A_81_H": "C'4551_loop"},
{"Q7Z7D3_A_82_E": "C'4552_loop"},
{"Q7Z7D3_A_83_F": "C'4553_loop"},
{"Q7Z7D3_A_84_K": "C'4554_loop"},
{"Q7Z7D3_A_85_E": "C'4555_loop"},
{"Q7Z7D3_A_86_G": "C'4556_loop"},
{"Q7Z7D3_A_87_K": "C'4557_loop"},
{"Q7Z7D3_A_88_D": "C'4558_loop"},
{"Q7Z7D3_A_89_E": "C'4559_loop"},
{"Q7Z7D3_A_90_L": "C'4560_loop"},
{"Q7Z7D3_A_91_S": "D6540_loop"},
{"Q7Z7D3_A_92_E": "D6541_loop"},
{"Q7Z7D3_A_93_Q": "D6542_loop"},
{"Q7Z7D3_A_94_D": "D6543_loop"},
{"Q7Z7D3_A_95_E": "D6544_loop"},
{"Q7Z7D3_A_96_M": "D6545_loop"},
{"Q7Z7D3_A_97_F": "D6546_loop"},
{"Q7Z7D3_A_98_R": "D6547_loop"},
{"Q7Z7D3_A_99_G": "D6548_loop"},
{"Q7Z7D3_A_100_R": "D6549"},
{"Q7Z7D3_A_101_T": "D6550"},
{"Q7Z7D3_A_102_A": "D6551"},
{"Q7Z7D3_A_103_V": "D6552"},
{"Q7Z7D3_A_104_F": "D6553"},
{"Q7Z7D3_A_105_A": "D6554_loop"},
{"Q7Z7D3_A_106_D": "D6555_loop"},
{"Q7Z7D3_A_107_Q": "D6556_loop"},
{"Q7Z7D3_A_108_V": "E7542_loop"},
{"Q7Z7D3_A_109_I": "E7543_loop"},
{"Q7Z7D3_A_110_V": "E7544_loop"},
{"Q7Z7D3_A_111_G": "E7545"},
{"Q7Z7D3_A_112_N": "E7546"},
{"Q7Z7D3_A_113_A": "E7547"},
{"Q7Z7D3_A_114_S": "E7548"},
{"Q7Z7D3_A_115_L": "E7549"},
{"Q7Z7D3_A_116_R": "E7550"},
{"Q7Z7D3_A_117_L": "E7551"},
{"Q7Z7D3_A_118_K": "E7552_loop"},
{"Q7Z7D3_A_119_N": "E7553_loop"},
{"Q7Z7D3_A_120_V": "E7554_loop"},
{"Q7Z7D3_A_121_Q": "E7555_loop"},
{"Q7Z7D3_A_122_L": "F8542_loop"},
{"Q7Z7D3_A_123_T": "F8543_loop"},
{"Q7Z7D3_A_124_D": "F8544_loop"},
{"Q7Z7D3_A_125_A": "F8545_loop"},
{"Q7Z7D3_A_126_G": "F8546"},
{"Q7Z7D3_A_127_T": "F8547"},
{"Q7Z7D3_A_128_Y": "F8548"},
{"Q7Z7D3_A_129_K": "F8549"},
{"Q7Z7D3_A_130_C": "F8550"},
{"Q7Z7D3_A_131_Y": "F8551"},
{"Q7Z7D3_A_132_I": "F8552"},
{"Q7Z7D3_A_133_I": "F8553"},
{"Q7Z7D3_A_134_T": "F8554"},
{"Q7Z7D3_A_135_S": "F8555_loop"},
{"Q7Z7D3_A_136_K": "G9545_loop"},
{"Q7Z7D3_A_137_G": "G9546"},
{"Q7Z7D3_A_138_K": "G9547"},
{"Q7Z7D3_A_139_G": "G9548"},
{"Q7Z7D3_A_140_N": "G9549"},
{"Q7Z7D3_A_141_A": "G9550"},
{"Q7Z7D3_A_142_N": "G9551"},
{"Q7Z7D3_A_143_L": "G9552"},
{"Q7Z7D3_A_144_E": "G9553"},
{"Q7Z7D3_A_145_Y": "G9554"},
{"Q7Z7D3_A_146_K": "G9555"},
{"Q7Z7D3_A_147_T": "G9556"},
{"Q7Z7D3_A_148_G": "G9557"},
{"Q7Z7D3_A_257_K": "G+9659"},
{"Q7Z7D3_A_258_A": "G+9660"},
{"Q7Z7D3_A_259_S": "G+9661"},
{"Q7Z7D3_A_260_L": "G+9662"},
{"Q7Z7D3_A_261_C": "G+9663"},
{"Q7Z7D3_A_262_V": "G+9664"},
{"Q7Z7D3_A_263_S": "G+9665"},
{"Q7Z7D3_A_264_S": "G+9666"},
],
},
"Q7Z7D3_A,1_152:255:820": {
"refpdbname":"VTCN1_Q7Z7D3_human_C1-n2", "score":1, "seqid":1, "nresAlign":104, "data": [{"Q7Z7D3_A_152_M": "A1547"},
{"Q7Z7D3_A_153_P": "A1548"},
{"Q7Z7D3_A_154_E": "A1549"},
{"Q7Z7D3_A_155_V": "A1550"},
{"Q7Z7D3_A_156_N": "A1551"},
{"Q7Z7D3_A_157_V": "A1552"},
{"Q7Z7D3_A_158_D": "A1553_loop"},
{"Q7Z7D3_A_159_Y": "A1554_loop"},
{"Q7Z7D3_A_160_N": "A1555_loop"},
{"Q7Z7D3_A_161_A": "A1556_loop"},
{"Q7Z7D3_A_162_S": "B2544_loop"},
{"Q7Z7D3_A_163_S": "B2545_loop"},
{"Q7Z7D3_A_164_E": "B2546_loop"},
{"Q7Z7D3_A_165_T": "B2547"},
{"Q7Z7D3_A_166_L": "B2548"},
{"Q7Z7D3_A_167_R": "B2549"},
{"Q7Z7D3_A_168_C": "B2550"},
{"Q7Z7D3_A_169_E": "B2551"},
{"Q7Z7D3_A_170_A": "B2552"},
{"Q7Z7D3_A_171_P": "B2553"},
{"Q7Z7D3_A_172_R": "B2554"},
{"Q7Z7D3_A_173_W": "B2555"},
{"Q7Z7D3_A_174_F": "B2556"},
{"Q7Z7D3_A_175_P": "B2557_loop"},
{"Q7Z7D3_A_176_Q": "B2558_loop"},
{"Q7Z7D3_A_177_P": "C3546_loop"},
{"Q7Z7D3_A_178_T": "C3547"},
{"Q7Z7D3_A_179_V": "C3548"},
{"Q7Z7D3_A_180_V": "C3549"},
{"Q7Z7D3_A_181_W": "C3550"},
{"Q7Z7D3_A_182_A": "C3551"},
{"Q7Z7D3_A_183_S": "C3552"},
{"Q7Z7D3_A_184_Q": "C3553"},
{"Q7Z7D3_A_185_V": "C3554_loop"},
{"Q7Z7D3_A_186_D": "C3555_loop"},
{"Q7Z7D3_A_187_Q": "C'4546_loop"},
{"Q7Z7D3_A_188_G": "C'4547_loop"},
{"Q7Z7D3_A_189_A": "C'4548"},
{"Q7Z7D3_A_190_N": "C'4549"},
{"Q7Z7D3_A_191_F": "C'4550"},
{"Q7Z7D3_A_192_S": "C'4551_loop"},
{"Q7Z7D3_A_193_E": "D6548_loop"},
{"Q7Z7D3_A_194_V": "D6549"},
{"Q7Z7D3_A_195_S": "D6550"},
{"Q7Z7D3_A_196_N": "D6551"},
{"Q7Z7D3_A_197_T": "D6552"},
{"Q7Z7D3_A_198_S": "D6553"},
{"Q7Z7D3_A_199_F": "D6554"},
{"Q7Z7D3_A_200_E": "D6555"},
{"Q7Z7D3_A_201_L": "D6556"},
{"Q7Z7D3_A_202_N": "D6557_loop"},
{"Q7Z7D3_A_203_S": "D6558_loop"},
{"Q7Z7D3_A_204_E": "D6559_loop"},
{"Q7Z7D3_A_205_N": "E7541_loop"},
{"Q7Z7D3_A_206_V": "E7542_loop"},
{"Q7Z7D3_A_207_T": "E7543_loop"},
{"Q7Z7D3_A_208_M": "E7544"},
{"Q7Z7D3_A_209_K": "E7545"},
{"Q7Z7D3_A_210_V": "E7546"},
{"Q7Z7D3_A_211_V": "E7547"},
{"Q7Z7D3_A_212_S": "E7548"},
{"Q7Z7D3_A_213_V": "E7549"},
{"Q7Z7D3_A_214_L": "E7550"},
{"Q7Z7D3_A_215_Y": "E7551"},
{"Q7Z7D3_A_216_N": "E7552_loop"},
{"Q7Z7D3_A_217_V": "E7553_loop"},
{"Q7Z7D3_A_218_T": "E7554_loop"},
{"Q7Z7D3_A_219_I": "F8544_loop"},
{"Q7Z7D3_A_220_N": "F8545_loop"},
{"Q7Z7D3_A_221_N": "F8546_loop"},
{"Q7Z7D3_A_222_T": "F8547"},
{"Q7Z7D3_A_223_Y": "F8548"},
{"Q7Z7D3_A_224_S": "F8549"},
{"Q7Z7D3_A_225_C": "F8550"},
{"Q7Z7D3_A_226_M": "F8551"},
{"Q7Z7D3_A_227_I": "F8552"},
{"Q7Z7D3_A_228_E": "F8553"},
{"Q7Z7D3_A_229_N": "F8554_loop"},
{"Q7Z7D3_A_230_D": "F8555_loop"},
{"Q7Z7D3_A_231_I": "G9545_loop"},
{"Q7Z7D3_A_232_A": "G9546"},
{"Q7Z7D3_A_233_K": "G9547"},
{"Q7Z7D3_A_234_A": "G9548"},
{"Q7Z7D3_A_235_T": "G9549"},
{"Q7Z7D3_A_236_G": "G9550"},
{"Q7Z7D3_A_237_D": "G9551"},
{"Q7Z7D3_A_238_I": "G9552"},
{"Q7Z7D3_A_239_K": "G9553"},
{"Q7Z7D3_A_240_V": "G9554"},
{"Q7Z7D3_A_241_T": "G9555_loop"},
{"Q7Z7D3_A_242_E": "G9556_loop"},
{"Q7Z7D3_A_243_S": "G9557_loop"},
{"Q7Z7D3_A_244_E": "G9558_loop"},
{"Q7Z7D3_A_245_I": "G+9659"},
{"Q7Z7D3_A_246_K": "G+9660"},
{"Q7Z7D3_A_247_R": "G+9661"},
{"Q7Z7D3_A_248_R": "G+9662"},
{"Q7Z7D3_A_249_S": "G+9663"},
{"Q7Z7D3_A_250_H": "G+9664"},
{"Q7Z7D3_A_251_L": "G+9665"},
{"Q7Z7D3_A_252_Q": "G+9666"},
{"Q7Z7D3_A_253_L": "G+9667"},
],
},
}},
]}},


]
